LICENSE.txt
README.md
setup.py
fastreqshttps/__init__.py
fastreqshttps/browser.py
fastreqshttps/config.py
fastreqshttps/encoder.py
fastreqshttps/init.py
fastreqshttps/receiver.py
fastreqshttps.egg-info/PKG-INFO
fastreqshttps.egg-info/SOURCES.txt
fastreqshttps.egg-info/dependency_links.txt
fastreqshttps.egg-info/requires.txt
fastreqshttps.egg-info/top_level.txt
fastreqshttps/utils/__init__.py
fastreqshttps/utils/database.py
fastreqshttps/utils/file.py
fastreqshttps/utils/request.py