Metadata-Version: 2.1
Name: fastreqshttps
Version: 0.2
Summary: Make https requests all over the web.
Home-page: https://github.com/adripython69/fastreqshttps
Download-URL: https://github.com/mackenzieoeoe/fastreqshttps/archive/refs/tags/oui.tar.gz
Author: adrien
Author-email: adrien@f1v5o.gpa.lu
License: MIT
License-File: LICENSE.txt
